botris/__init__.py
botris/bots/__init__.py
botris/bots/bot/__init__.py
botris/bots/bot/bot.py
botris/bots/randombot/__init__.py
botris/bots/randombot/randombot.py
botris/engine/__init__.py
botris/engine/models.py
botris/engine/move_generator.py
botris/engine/pieces.py
botris/engine/tetris.py
botris/engine/utils.py
botris/interface/__init__.py
botris/interface/handlers.py
botris/interface/interface.py
botris/interface/models.py
botris/interface/websocket_client.py
botris_interface-0.1.21.dist-info/LICENSE
botris_interface-0.1.21.dist-info/METADATA
botris_interface-0.1.21.dist-info/WHEEL
botris_interface-0.1.21.dist-info/RECORD
