Metadata-Version: 2.1
Name: botris-interface
Version: 0.1.21
Summary: A performant library designed for creating and managing bots in a Tetris-like game environment. This library offers various tools and features to build, test, and deploy bots efficiently to Botris.
License: MIT
Author: Nathanael Lu
Author-email: info@lunathanael.dev
Requires-Python: >=3.10,<4.0
Classifier: License :: OSI Approved :: MIT License
Classifier: Programming Language :: Python :: 3
Classifier: Programming Language :: Python :: 3.10
Classifier: Programming Language :: Python :: 3.11
Classifier: Programming Language :: Python :: 3.12
Requires-Dist: colorama (>=0.4.6,<0.5.0)
Requires-Dist: pillow (>=10.4.0,<11.0.0)
Requires-Dist: protobuf (>=5.27.3,<6.0.0)
Requires-Dist: pybind11 (>=2.13.3,<3.0.0)
Requires-Dist: pydantic (>=2.8.2,<3.0.0)
Requires-Dist: setuptools (>=72.2.0,<73.0.0)
Requires-Dist: websockets (>=12.0,<13.0)
